optical_flow_frame_utils/__init__.py
optical_flow_frame_utils/__main__.py
optical_flow_frame_utils/frame_utils.py
optical_flow_frame_utils-0.0.1.dist-info/METADATA
optical_flow_frame_utils-0.0.1.dist-info/WHEEL
optical_flow_frame_utils-0.0.1.dist-info/entry_points.txt
optical_flow_frame_utils-0.0.1.dist-info/top_level.txt
optical_flow_frame_utils-0.0.1.dist-info/RECORD
