Metadata-Version: 2.1
Name: optical-flow-frame-utils
Version: 0.0.1
Summary: Lib for most popular data format read and write of optical flow in python
Home-page: UNKNOWN
Author: Real Python
Author-email: info@realpython.com
License: MIT
Platform: UNKNOWN
Classifier: License :: OSI Approved :: MIT License
Classifier: Programming Language :: Python :: 3
Classifier: Programming Language :: Python :: 3.7
Requires-Dist: Pillow
Requires-Dist: numpy
Requires-Dist: opencv-python
